{"nodes": [{"id": "src_libs_cpp_hash_lib_wrapper_cc", "label": "cpp_hash_lib_wrapper.cc", "file_type": "code", "source_file": "src/libs/cpp_hash_lib_wrapper.cc", "source_location": "L1"}, {"id": "cpp_hash_lib_wrapper_key", "label": "key()", "file_type": "code", "source_file": "src/libs/cpp_hash_lib_wrapper.cc", "source_location": "L17"}, {"id": "cpp_hash_lib_wrapper_cpp_hash_table_access_create", "label": "cpp_hash_table_access_create()", "file_type": "code", "source_file": "src/libs/cpp_hash_lib_wrapper.cc", "source_location": "L50"}], "edges": [{"source": "src_libs_cpp_hash_lib_wrapper_cc", "target": "cpp_hash_lib_wrapper", "relation": "imports", "confidence": "EXTRACTED", "source_file": "src/libs/cpp_hash_lib_wrapper.cc", "source_location": "L1", "weight": 1.0}, {"source": "src_libs_cpp_hash_lib_wrapper_cc", "target": "iostream", "relation": "imports", "confidence": "EXTRACTED", "source_file": "src/libs/cpp_hash_lib_wrapper.cc", "source_location": "L3", "weight": 1.0}, {"source": "src_libs_cpp_hash_lib_wrapper_cc", "target": "unordered_map", "relation": "imports", "confidence": "EXTRACTED", "source_file": "src/libs/cpp_hash_lib_wrapper.cc", "source_location": "L4", "weight": 1.0}, {"source": "src_libs_cpp_hash_lib_wrapper_cc", "target": "vector", "relation": "imports", "confidence": "EXTRACTED", "source_file": "src/libs/cpp_hash_lib_wrapper.cc", "source_location": "L5", "weight": 1.0}, {"source": "src_libs_cpp_hash_lib_wrapper_cc", "target": "global_defs", "relation": "imports", "confidence": "EXTRACTED", "source_file": "src/libs/cpp_hash_lib_wrapper.cc", "source_location": "L8", "weight": 1.0}, {"source": "src_libs_cpp_hash_lib_wrapper_cc", "target": "cpp_hash_lib_wrapper_key", "relation": "contains", "confidence": "EXTRACTED", "source_file": "src/libs/cpp_hash_lib_wrapper.cc", "source_location": "L17", "weight": 1.0}, {"source": "src_libs_cpp_hash_lib_wrapper_cc", "target": "cpp_hash_lib_wrapper_key", "relation": "contains", "confidence": "EXTRACTED", "source_file": "src/libs/cpp_hash_lib_wrapper.cc", "source_location": "L18", "weight": 1.0}, {"source": "src_libs_cpp_hash_lib_wrapper_cc", "target": "cpp_hash_lib_wrapper_cpp_hash_table_access_create", "relation": "contains", "confidence": "EXTRACTED", "source_file": "src/libs/cpp_hash_lib_wrapper.cc", "source_location": "L50", "weight": 1.0}], "raw_calls": [{"caller_nid": "cpp_hash_lib_wrapper_cpp_hash_table_access_create", "callee": "find", "source_file": "src/libs/cpp_hash_lib_wrapper.cc", "source_location": "L55"}, {"caller_nid": "cpp_hash_lib_wrapper_cpp_hash_table_access_create", "callee": "end", "source_file": "src/libs/cpp_hash_lib_wrapper.cc", "source_location": "L56"}, {"caller_nid": "cpp_hash_lib_wrapper_cpp_hash_table_access_create", "callee": "emplace", "source_file": "src/libs/cpp_hash_lib_wrapper.cc", "source_location": "L59"}]}